README
setup.py
bambu_formatrules/__init__.py
bambu_formatrules/helpers.py
bambu_formatrules.egg-info/PKG-INFO
bambu_formatrules.egg-info/SOURCES.txt
bambu_formatrules.egg-info/dependency_links.txt
bambu_formatrules.egg-info/requires.txt
bambu_formatrules.egg-info/top_level.txt
bambu_formatrules/formatters/__init__.py
bambu_formatrules/formatters/block.py
bambu_formatrules/formatters/bookmark.py
bambu_formatrules/templatetags/__init__.py
bambu_formatrules/templatetags/formatrules.py