Metadata-Version: 1.1
Name: bambu-formatrules
Version: 2.0
Summary: Syntactical sugar ontop of Markdown for adding extra formatting, expressed in a human-readable way.
Home-page: http://pypi.python.org/pypi/bambu-formatrules
Author: Steadman
Author-email: mark@steadman.io
License: UNKNOWN
Platform: UNKNOWN
Classifier: Development Status :: 4 - Beta
Classifier: Environment :: Web Environment
Classifier: Framework :: Django
